petrel_chicks/__init__.py
petrel_chicks/calculate_mass_loss_rates.py
petrel_chicks/cli.py
petrel_chicks/error_estimator_function.py
petrel_chicks/filter_per_season.py
petrel_chicks/fit_model_for_peak_mass.py
petrel_chicks/petrel_age_predictor.py
petrel_chicks/plot_peak_mass_model.py
petrel_chicks-0.7.2.dist-info/entry_points.txt
petrel_chicks-0.7.2.dist-info/licenses/LICENSE
petrel_chicks-0.7.2.dist-info/WHEEL
petrel_chicks-0.7.2.dist-info/METADATA
petrel_chicks-0.7.2.dist-info/RECORD
