Metadata-Version: 2.4
Name: petrel_chicks
Version: 0.7.2
Summary: A module to petrel_chicks
Home-page: https://github.com/IslasGECI/petrel_chicks
Author: Ciencia de Datos • GECI
Author-email: ciencia.datos@islas.org.mx
Requires-Python: >=3.9
Classifier: License :: OSI Approved :: GNU General Public License v3 or later (GPLv3+)
License-File: LICENSE
Requires-Dist: geci-plots==0.*
Requires-Dist: lmfit
Requires-Dist: mean-differences-mc
Requires-Dist: numpy==1.26.4
Requires-Dist: pandasql
Requires-Dist: scikit-learn==1.1.3
Requires-Dist: typer[all]
